mahjong_utils/__init__.py
mahjong_utils/bridge/__init__.py
mahjong_utils/bridge/protocol.py
mahjong_utils/bridge/http/__init__.py
mahjong_utils/bridge/js/__init__.py
mahjong_utils/bridge/js/mahjong-utils-entry.js
mahjong_utils/bridge/js/mahjong-utils-entry.js.map
mahjong_utils/bridge/webapi_jar/__init__.py
mahjong_utils/hora/__init__.py
mahjong_utils/hora/hora.py
mahjong_utils/hora/models.py
mahjong_utils/models/__init__.py
mahjong_utils/models/furo.py
mahjong_utils/models/hand.py
mahjong_utils/models/hand_pattern.py
mahjong_utils/models/mentsu.py
mahjong_utils/models/tatsu.py
mahjong_utils/models/tile.py
mahjong_utils/models/tile_type.py
mahjong_utils/models/wind.py
mahjong_utils/point_by_han_hu/__init__.py
mahjong_utils/point_by_han_hu/models.py
mahjong_utils/point_by_han_hu/point_by_han_hu.py
mahjong_utils/shanten/__init__.py
mahjong_utils/shanten/models.py
mahjong_utils/shanten/shanten.py
mahjong_utils/yaku/__init__.py
mahjong_utils/yaku/all_yaku.py
mahjong_utils/yaku/common.py
mahjong_utils/yaku/extra.py
mahjong_utils/yaku/yaku.py
mahjong_utils/yaku/yakuman.py
mahjong_utils-0.7.7.dist-info/METADATA
mahjong_utils-0.7.7.dist-info/WHEEL
mahjong_utils-0.7.7.dist-info/top_level.txt
mahjong_utils-0.7.7.dist-info/RECORD
