Metadata-Version: 2.2
Name: mahjong-utils
Version: 0.7.7
Summary: 日麻小工具
Home-page: https://github.com/ssttkkl/mahjong-utils
Author: ssttkkl
Author-email: huang.wen.long@hotmail.com
License: MIT
Requires-Dist: pydantic<2.0.0,>=1.9.0
Requires-Dist: mini-racer>=0.12.4
Requires-Dist: stringcase>=1.2.0
Dynamic: author
Dynamic: author-email
Dynamic: description
Dynamic: description-content-type
Dynamic: home-page
Dynamic: license
Dynamic: requires-dist
Dynamic: summary
